filesystem_pysdk/__init__.py
filesystem_pysdk/bucket.py
filesystem_pysdk/client.py
filesystem_pysdk/file.py
filesystem_pysdk/user.py
filesystem_pysdk-2.0.0.dist-info/LICENSE
filesystem_pysdk-2.0.0.dist-info/METADATA
filesystem_pysdk-2.0.0.dist-info/WHEEL
filesystem_pysdk-2.0.0.dist-info/RECORD
