Metadata-Version: 2.1
Name: filesystem-pysdk
Version: 2.0.0
Summary: python filesystem sdk
Home-page: https://github.com/i-curve/filesystem-pysdk
License: BSD-3-Clause
Author: i-curve
Author-email: i-curve@qq.com
Requires-Python: >=3.9,<4.0
Classifier: License :: OSI Approved :: BSD License
Classifier: Programming Language :: Python :: 3
Classifier: Programming Language :: Python :: 3.9
Classifier: Programming Language :: Python :: 3.10
Classifier: Programming Language :: Python :: 3.11
Classifier: Programming Language :: Python :: 3.12
Requires-Dist: requests (>=2.13,<3.0)
Project-URL: Repository, https://github.com/i-curve/filesystem-pysdk
